scratchai/__init__.py
scratchai/cart.py
scratchai/decision_forests.py
scratchai/forests.py
scratchai/linear_models.py
scratchai/metrics.py
scratchai/plotting.py
scratchai/preproccessing.py
scratchai/trees.py
scratchai/build/__init__.py
scratchai/build/_internal/__init__.py
scratchai/build/_internal/_activation.py
scratchai/build/_internal/_block.py
scratchai/build/_internal/_create.py
scratchai/build/_internal/_loss.py
scratchai/metrics/__init__.py
scratchai/metrics/_internel/__init__.py
scratchai/metrics/_internel/_metrics.py
scratchai/preproccessing/__init__.py
scratchai/preproccessing/_internal/__init__.py
scratchai/preproccessing/_internal/_preproccessing.py
tests/__init__.py
tests/build.py
tests/data.py
tests/forests.py
tests/linear_models.py
tests/trees.py
scratchai-0.7.5.dist-info/METADATA
scratchai-0.7.5.dist-info/WHEEL
scratchai-0.7.5.dist-info/top_level.txt
scratchai-0.7.5.dist-info/RECORD
