Metadata-Version: 2.1
Name: scratchai
Version: 0.7.5
Summary: Python librarie for machine learning
Author: Mohamed Marghoub
Author-email: <marghoubmohamed2@email.com>
Keywords: python,machine_learning,data_science
Classifier: Intended Audience :: Education
Classifier: Programming Language :: Python :: 2
Classifier: Programming Language :: Python :: 3
Classifier: Operating System :: MacOS :: MacOS X
Classifier: Operating System :: Microsoft :: Windows
Requires-Dist: numpy
Requires-Dist: joblib
